kap_sdk/__init__.py
kap_sdk/_companies.py
kap_sdk/_company_info.py
kap_sdk/_financial_report.py
kap_sdk/_indices.py
kap_sdk/_kap_sdk_example.py
kap_sdk/_search_oid.py
kap_sdk/_sectors.py
kap_sdk/kap_client.py
kap_sdk-0.1.23.dist-info/METADATA
kap_sdk-0.1.23.dist-info/WHEEL
kap_sdk-0.1.23.dist-info/top_level.txt
kap_sdk-0.1.23.dist-info/RECORD
