Metadata-Version: 2.4
Name: kap_sdk
Version: 0.1.23
Summary: KAP (Kamuyu Aydınlatma Platformu) üzerinden veri çekmek için bir Python SDK
Author-email: Mustafa Kilic <mustafa@example.com>
License: MIT
Keywords: kap,public disclosure platform,data scraping,financial data
Requires-Python: >=3.8.1
Requires-Dist: requests>=2.28.1
Requires-Dist: beautifulsoup4>=4.11.1
Requires-Dist: pyppeteer>=1.0.2
Requires-Dist: diskcache>=5.4.0
Requires-Dist: pandas>=1.5.0
Requires-Dist: lxml>=4.9.1
Requires-Dist: tomli>=2.0.1
Provides-Extra: dev
Requires-Dist: pytest>=7.3.1; extra == "dev"
Requires-Dist: black>=23.3.0; extra == "dev"
Requires-Dist: isort>=5.12.0; extra == "dev"
Requires-Dist: flake8>=6.0.0; extra == "dev"
